{
  "type": "File",
  "start": 0,
  "end": 958,
  "loc": {
    "start": {
      "line": 1,
      "column": 0
    },
    "end": {
      "line": 36,
      "column": 0
    }
  },
  "program": {
    "type": "Program",
    "start": 0,
    "end": 958,
    "loc": {
      "start": {
        "line": 1,
        "column": 0
      },
      "end": {
        "line": 36,
        "column": 0
      }
    },
    "sourceType": "module",
    "body": [
      {
        "type": "ImportDeclaration",
        "start": 72,
        "end": 141,
        "loc": {
          "start": {
            "line": 8,
            "column": 0
          },
          "end": {
            "line": 8,
            "column": 69
          }
        },
        "specifiers": [
          {
            "type": "ImportDefaultSpecifier",
            "start": 79,
            "end": 91,
            "loc": {
              "start": {
                "line": 8,
                "column": 7
              },
              "end": {
                "line": 8,
                "column": 19
              }
            },
            "local": {
              "type": "Identifier",
              "start": 79,
              "end": 91,
              "loc": {
                "start": {
                  "line": 8,
                  "column": 7
                },
                "end": {
                  "line": 8,
                  "column": 19
                },
                "identifierName": "AsyncStorage"
              },
              "name": "AsyncStorage",
              "leadingComments": null
            },
            "leadingComments": null
          }
        ],
        "source": {
          "type": "StringLiteral",
          "start": 97,
          "end": 140,
          "loc": {
            "start": {
              "line": 8,
              "column": 25
            },
            "end": {
              "line": 8,
              "column": 68
            }
          },
          "extra": {
            "rawValue": "@react-native-async-storage/async-storage",
            "raw": "'@react-native-async-storage/async-storage'"
          },
          "value": "@react-native-async-storage/async-storage"
        },
        "leadingComments": [
          {
            "type": "CommentBlock",
            "value": "*\n * File for handling async storage requests\n ",
            "start": 0,
            "end": 51,
            "loc": {
              "start": {
                "line": 1,
                "column": 0
              },
              "end": {
                "line": 3,
                "column": 3
              }
            }
          },
          {
            "type": "CommentBlock",
            "value": "*\n * Imports\n ",
            "start": 53,
            "end": 71,
            "loc": {
              "start": {
                "line": 5,
                "column": 0
              },
              "end": {
                "line": 7,
                "column": 3
              }
            }
          }
        ],
        "trailingComments": [
          {
            "type": "CommentBlock",
            "value": "*\n * This method is used to store data in async storage\n * @param {String} key Unique key for identifying data stored in async storage\n * @param {String} data Data to be stored\n ",
            "start": 143,
            "end": 325,
            "loc": {
              "start": {
                "line": 10,
                "column": 0
              },
              "end": {
                "line": 14,
                "column": 3
              }
            }
          }
        ]
      },
      {
        "type": "ExportNamedDeclaration",
        "start": 326,
        "end": 410,
        "loc": {
          "start": {
            "line": 15,
            "column": 0
          },
          "end": {
            "line": 17,
            "column": 2
          }
        },
        "specifiers": [],
        "source": null,
        "declaration": {
          "type": "VariableDeclaration",
          "start": 333,
          "end": 410,
          "loc": {
            "start": {
              "line": 15,
              "column": 7
            },
            "end": {
              "line": 17,
              "column": 2
            }
          },
          "declarations": [
            {
              "type": "VariableDeclarator",
              "start": 339,
              "end": 409,
              "loc": {
                "start": {
                  "line": 15,
                  "column": 13
                },
                "end": {
                  "line": 17,
                  "column": 1
                }
              },
              "id": {
                "type": "Identifier",
                "start": 339,
                "end": 347,
                "loc": {
                  "start": {
                    "line": 15,
                    "column": 13
                  },
                  "end": {
                    "line": 15,
                    "column": 21
                  },
                  "identifierName": "saveData"
                },
                "name": "saveData",
                "leadingComments": null
              },
              "init": {
                "type": "ArrowFunctionExpression",
                "start": 350,
                "end": 409,
                "loc": {
                  "start": {
                    "line": 15,
                    "column": 24
                  },
                  "end": {
                    "line": 17,
                    "column": 1
                  }
                },
                "id": {
                  "type": "Identifier",
                  "start": 339,
                  "end": 347,
                  "loc": {
                    "start": {
                      "line": 15,
                      "column": 13
                    },
                    "end": {
                      "line": 15,
                      "column": 21
                    },
                    "identifierName": "saveData"
                  },
                  "name": "saveData",
                  "leadingComments": null
                },
                "generator": false,
                "expression": false,
                "async": true,
                "params": [
                  {
                    "type": "Identifier",
                    "start": 357,
                    "end": 360,
                    "loc": {
                      "start": {
                        "line": 15,
                        "column": 31
                      },
                      "end": {
                        "line": 15,
                        "column": 34
                      },
                      "identifierName": "key"
                    },
                    "name": "key"
                  },
                  {
                    "type": "Identifier",
                    "start": 362,
                    "end": 366,
                    "loc": {
                      "start": {
                        "line": 15,
                        "column": 36
                      },
                      "end": {
                        "line": 15,
                        "column": 40
                      },
                      "identifierName": "data"
                    },
                    "name": "data"
                  }
                ],
                "body": {
                  "type": "BlockStatement",
                  "start": 371,
                  "end": 409,
                  "loc": {
                    "start": {
                      "line": 15,
                      "column": 45
                    },
                    "end": {
                      "line": 17,
                      "column": 1
                    }
                  },
                  "body": [
                    {
                      "type": "ExpressionStatement",
                      "start": 375,
                      "end": 407,
                      "loc": {
                        "start": {
                          "line": 16,
                          "column": 2
                        },
                        "end": {
                          "line": 16,
                          "column": 34
                        }
                      },
                      "expression": {
                        "type": "CallExpression",
                        "start": 375,
                        "end": 406,
                        "loc": {
                          "start": {
                            "line": 16,
                            "column": 2
                          },
                          "end": {
                            "line": 16,
                            "column": 33
                          }
                        },
                        "callee": {
                          "type": "MemberExpression",
                          "start": 375,
                          "end": 395,
                          "loc": {
                            "start": {
                              "line": 16,
                              "column": 2
                            },
                            "end": {
                              "line": 16,
                              "column": 22
                            }
                          },
                          "object": {
                            "type": "Identifier",
                            "start": 375,
                            "end": 387,
                            "loc": {
                              "start": {
                                "line": 16,
                                "column": 2
                              },
                              "end": {
                                "line": 16,
                                "column": 14
                              },
                              "identifierName": "AsyncStorage"
                            },
                            "name": "AsyncStorage"
                          },
                          "property": {
                            "type": "Identifier",
                            "start": 388,
                            "end": 395,
                            "loc": {
                              "start": {
                                "line": 16,
                                "column": 15
                              },
                              "end": {
                                "line": 16,
                                "column": 22
                              },
                              "identifierName": "setItem"
                            },
                            "name": "setItem"
                          },
                          "computed": false
                        },
                        "arguments": [
                          {
                            "type": "Identifier",
                            "start": 396,
                            "end": 399,
                            "loc": {
                              "start": {
                                "line": 16,
                                "column": 23
                              },
                              "end": {
                                "line": 16,
                                "column": 26
                              },
                              "identifierName": "key"
                            },
                            "name": "key"
                          },
                          {
                            "type": "Identifier",
                            "start": 401,
                            "end": 405,
                            "loc": {
                              "start": {
                                "line": 16,
                                "column": 28
                              },
                              "end": {
                                "line": 16,
                                "column": 32
                              },
                              "identifierName": "data"
                            },
                            "name": "data"
                          }
                        ]
                      }
                    }
                  ],
                  "directives": []
                }
              },
              "leadingComments": null
            }
          ],
          "kind": "const",
          "leadingComments": [
            {
              "type": "CommentBlock",
              "value": "*\n * This method is used to store data in async storage\n * @param {String} key Unique key for identifying data stored in async storage\n * @param {String} data Data to be stored\n ",
              "start": 143,
              "end": 325,
              "loc": {
                "start": {
                  "line": 10,
                  "column": 0
                },
                "end": {
                  "line": 14,
                  "column": 3
                }
              }
            }
          ],
          "trailingComments": [
            {
              "type": "CommentBlock",
              "value": "*\n * This method is used get data from async storage\n * @param {String} key Unique key for identifying data stored in async storage\n * @returns Value obtained from async storage against given key\n ",
              "start": 412,
              "end": 613,
              "loc": {
                "start": {
                  "line": 19,
                  "column": 0
                },
                "end": {
                  "line": 23,
                  "column": 3
                }
              }
            }
          ]
        },
        "leadingComments": [
          {
            "type": "CommentBlock",
            "value": "*\n * This method is used to store data in async storage\n * @param {String} key Unique key for identifying data stored in async storage\n * @param {String} data Data to be stored\n ",
            "start": 143,
            "end": 325,
            "loc": {
              "start": {
                "line": 10,
                "column": 0
              },
              "end": {
                "line": 14,
                "column": 3
              }
            }
          }
        ],
        "trailingComments": [
          {
            "type": "CommentBlock",
            "value": "*\n * This method is used get data from async storage\n * @param {String} key Unique key for identifying data stored in async storage\n * @returns Value obtained from async storage against given key\n ",
            "start": 412,
            "end": 613,
            "loc": {
              "start": {
                "line": 19,
                "column": 0
              },
              "end": {
                "line": 23,
                "column": 3
              }
            }
          }
        ]
      },
      {
        "type": "ExportNamedDeclaration",
        "start": 614,
        "end": 719,
        "loc": {
          "start": {
            "line": 24,
            "column": 0
          },
          "end": {
            "line": 27,
            "column": 2
          }
        },
        "specifiers": [],
        "source": null,
        "declaration": {
          "type": "VariableDeclaration",
          "start": 621,
          "end": 719,
          "loc": {
            "start": {
              "line": 24,
              "column": 7
            },
            "end": {
              "line": 27,
              "column": 2
            }
          },
          "declarations": [
            {
              "type": "VariableDeclarator",
              "start": 627,
              "end": 718,
              "loc": {
                "start": {
                  "line": 24,
                  "column": 13
                },
                "end": {
                  "line": 27,
                  "column": 1
                }
              },
              "id": {
                "type": "Identifier",
                "start": 627,
                "end": 634,
                "loc": {
                  "start": {
                    "line": 24,
                    "column": 13
                  },
                  "end": {
                    "line": 24,
                    "column": 20
                  },
                  "identifierName": "getData"
                },
                "name": "getData",
                "leadingComments": null
              },
              "init": {
                "type": "ArrowFunctionExpression",
                "start": 637,
                "end": 718,
                "loc": {
                  "start": {
                    "line": 24,
                    "column": 23
                  },
                  "end": {
                    "line": 27,
                    "column": 1
                  }
                },
                "id": {
                  "type": "Identifier",
                  "start": 627,
                  "end": 634,
                  "loc": {
                    "start": {
                      "line": 24,
                      "column": 13
                    },
                    "end": {
                      "line": 24,
                      "column": 20
                    },
                    "identifierName": "getData"
                  },
                  "name": "getData",
                  "leadingComments": null
                },
                "generator": false,
                "expression": false,
                "async": true,
                "params": [
                  {
                    "type": "Identifier",
                    "start": 643,
                    "end": 646,
                    "loc": {
                      "start": {
                        "line": 24,
                        "column": 29
                      },
                      "end": {
                        "line": 24,
                        "column": 32
                      },
                      "identifierName": "key"
                    },
                    "name": "key"
                  }
                ],
                "body": {
                  "type": "BlockStatement",
                  "start": 650,
                  "end": 718,
                  "loc": {
                    "start": {
                      "line": 24,
                      "column": 36
                    },
                    "end": {
                      "line": 27,
                      "column": 1
                    }
                  },
                  "body": [
                    {
                      "type": "VariableDeclaration",
                      "start": 654,
                      "end": 700,
                      "loc": {
                        "start": {
                          "line": 25,
                          "column": 2
                        },
                        "end": {
                          "line": 25,
                          "column": 48
                        }
                      },
                      "declarations": [
                        {
                          "type": "VariableDeclarator",
                          "start": 660,
                          "end": 699,
                          "loc": {
                            "start": {
                              "line": 25,
                              "column": 8
                            },
                            "end": {
                              "line": 25,
                              "column": 47
                            }
                          },
                          "id": {
                            "type": "Identifier",
                            "start": 660,
                            "end": 665,
                            "loc": {
                              "start": {
                                "line": 25,
                                "column": 8
                              },
                              "end": {
                                "line": 25,
                                "column": 13
                              },
                              "identifierName": "value"
                            },
                            "name": "value"
                          },
                          "init": {
                            "type": "AwaitExpression",
                            "start": 668,
                            "end": 699,
                            "loc": {
                              "start": {
                                "line": 25,
                                "column": 16
                              },
                              "end": {
                                "line": 25,
                                "column": 47
                              }
                            },
                            "argument": {
                              "type": "CallExpression",
                              "start": 674,
                              "end": 699,
                              "loc": {
                                "start": {
                                  "line": 25,
                                  "column": 22
                                },
                                "end": {
                                  "line": 25,
                                  "column": 47
                                }
                              },
                              "callee": {
                                "type": "MemberExpression",
                                "start": 674,
                                "end": 694,
                                "loc": {
                                  "start": {
                                    "line": 25,
                                    "column": 22
                                  },
                                  "end": {
                                    "line": 25,
                                    "column": 42
                                  }
                                },
                                "object": {
                                  "type": "Identifier",
                                  "start": 674,
                                  "end": 686,
                                  "loc": {
                                    "start": {
                                      "line": 25,
                                      "column": 22
                                    },
                                    "end": {
                                      "line": 25,
                                      "column": 34
                                    },
                                    "identifierName": "AsyncStorage"
                                  },
                                  "name": "AsyncStorage"
                                },
                                "property": {
                                  "type": "Identifier",
                                  "start": 687,
                                  "end": 694,
                                  "loc": {
                                    "start": {
                                      "line": 25,
                                      "column": 35
                                    },
                                    "end": {
                                      "line": 25,
                                      "column": 42
                                    },
                                    "identifierName": "getItem"
                                  },
                                  "name": "getItem"
                                },
                                "computed": false
                              },
                              "arguments": [
                                {
                                  "type": "Identifier",
                                  "start": 695,
                                  "end": 698,
                                  "loc": {
                                    "start": {
                                      "line": 25,
                                      "column": 43
                                    },
                                    "end": {
                                      "line": 25,
                                      "column": 46
                                    },
                                    "identifierName": "key"
                                  },
                                  "name": "key"
                                }
                              ]
                            }
                          }
                        }
                      ],
                      "kind": "const"
                    },
                    {
                      "type": "ReturnStatement",
                      "start": 703,
                      "end": 716,
                      "loc": {
                        "start": {
                          "line": 26,
                          "column": 2
                        },
                        "end": {
                          "line": 26,
                          "column": 15
                        }
                      },
                      "argument": {
                        "type": "Identifier",
                        "start": 710,
                        "end": 715,
                        "loc": {
                          "start": {
                            "line": 26,
                            "column": 9
                          },
                          "end": {
                            "line": 26,
                            "column": 14
                          },
                          "identifierName": "value"
                        },
                        "name": "value"
                      }
                    }
                  ],
                  "directives": []
                }
              },
              "leadingComments": null
            }
          ],
          "kind": "const",
          "leadingComments": [
            {
              "type": "CommentBlock",
              "value": "*\n * This method is used get data from async storage\n * @param {String} key Unique key for identifying data stored in async storage\n * @returns Value obtained from async storage against given key\n ",
              "start": 412,
              "end": 613,
              "loc": {
                "start": {
                  "line": 19,
                  "column": 0
                },
                "end": {
                  "line": 23,
                  "column": 3
                }
              }
            }
          ],
          "trailingComments": [
            {
              "type": "CommentBlock",
              "value": "*\n * This method is used remove data from async storage\n * @param {string} key Unique key for identifying data stored in async storage\n ",
              "start": 721,
              "end": 861,
              "loc": {
                "start": {
                  "line": 29,
                  "column": 0
                },
                "end": {
                  "line": 32,
                  "column": 3
                }
              }
            }
          ]
        },
        "leadingComments": [
          {
            "type": "CommentBlock",
            "value": "*\n * This method is used get data from async storage\n * @param {String} key Unique key for identifying data stored in async storage\n * @returns Value obtained from async storage against given key\n ",
            "start": 412,
            "end": 613,
            "loc": {
              "start": {
                "line": 19,
                "column": 0
              },
              "end": {
                "line": 23,
                "column": 3
              }
            }
          }
        ],
        "trailingComments": [
          {
            "type": "CommentBlock",
            "value": "*\n * This method is used remove data from async storage\n * @param {string} key Unique key for identifying data stored in async storage\n ",
            "start": 721,
            "end": 861,
            "loc": {
              "start": {
                "line": 29,
                "column": 0
              },
              "end": {
                "line": 32,
                "column": 3
              }
            }
          }
        ]
      },
      {
        "type": "ExportNamedDeclaration",
        "start": 862,
        "end": 957,
        "loc": {
          "start": {
            "line": 33,
            "column": 0
          },
          "end": {
            "line": 35,
            "column": 2
          }
        },
        "specifiers": [],
        "source": null,
        "declaration": {
          "type": "VariableDeclaration",
          "start": 869,
          "end": 957,
          "loc": {
            "start": {
              "line": 33,
              "column": 7
            },
            "end": {
              "line": 35,
              "column": 2
            }
          },
          "declarations": [
            {
              "type": "VariableDeclarator",
              "start": 875,
              "end": 956,
              "loc": {
                "start": {
                  "line": 33,
                  "column": 13
                },
                "end": {
                  "line": 35,
                  "column": 1
                }
              },
              "id": {
                "type": "Identifier",
                "start": 875,
                "end": 885,
                "loc": {
                  "start": {
                    "line": 33,
                    "column": 13
                  },
                  "end": {
                    "line": 33,
                    "column": 23
                  },
                  "identifierName": "removeData"
                },
                "name": "removeData",
                "leadingComments": null
              },
              "init": {
                "type": "ArrowFunctionExpression",
                "start": 888,
                "end": 956,
                "loc": {
                  "start": {
                    "line": 33,
                    "column": 26
                  },
                  "end": {
                    "line": 35,
                    "column": 1
                  }
                },
                "id": {
                  "type": "Identifier",
                  "start": 875,
                  "end": 885,
                  "loc": {
                    "start": {
                      "line": 33,
                      "column": 13
                    },
                    "end": {
                      "line": 33,
                      "column": 23
                    },
                    "identifierName": "removeData"
                  },
                  "name": "removeData",
                  "leadingComments": null
                },
                "generator": false,
                "expression": false,
                "async": true,
                "params": [
                  {
                    "type": "Identifier",
                    "start": 894,
                    "end": 897,
                    "loc": {
                      "start": {
                        "line": 33,
                        "column": 32
                      },
                      "end": {
                        "line": 33,
                        "column": 35
                      },
                      "identifierName": "key"
                    },
                    "name": "key"
                  }
                ],
                "body": {
                  "type": "BlockStatement",
                  "start": 901,
                  "end": 956,
                  "loc": {
                    "start": {
                      "line": 33,
                      "column": 39
                    },
                    "end": {
                      "line": 35,
                      "column": 1
                    }
                  },
                  "body": [
                    {
                      "type": "VariableDeclaration",
                      "start": 905,
                      "end": 954,
                      "loc": {
                        "start": {
                          "line": 34,
                          "column": 2
                        },
                        "end": {
                          "line": 34,
                          "column": 51
                        }
                      },
                      "declarations": [
                        {
                          "type": "VariableDeclarator",
                          "start": 911,
                          "end": 953,
                          "loc": {
                            "start": {
                              "line": 34,
                              "column": 8
                            },
                            "end": {
                              "line": 34,
                              "column": 50
                            }
                          },
                          "id": {
                            "type": "Identifier",
                            "start": 911,
                            "end": 916,
                            "loc": {
                              "start": {
                                "line": 34,
                                "column": 8
                              },
                              "end": {
                                "line": 34,
                                "column": 13
                              },
                              "identifierName": "value"
                            },
                            "name": "value"
                          },
                          "init": {
                            "type": "AwaitExpression",
                            "start": 919,
                            "end": 953,
                            "loc": {
                              "start": {
                                "line": 34,
                                "column": 16
                              },
                              "end": {
                                "line": 34,
                                "column": 50
                              }
                            },
                            "argument": {
                              "type": "CallExpression",
                              "start": 925,
                              "end": 953,
                              "loc": {
                                "start": {
                                  "line": 34,
                                  "column": 22
                                },
                                "end": {
                                  "line": 34,
                                  "column": 50
                                }
                              },
                              "callee": {
                                "type": "MemberExpression",
                                "start": 925,
                                "end": 948,
                                "loc": {
                                  "start": {
                                    "line": 34,
                                    "column": 22
                                  },
                                  "end": {
                                    "line": 34,
                                    "column": 45
                                  }
                                },
                                "object": {
                                  "type": "Identifier",
                                  "start": 925,
                                  "end": 937,
                                  "loc": {
                                    "start": {
                                      "line": 34,
                                      "column": 22
                                    },
                                    "end": {
                                      "line": 34,
                                      "column": 34
                                    },
                                    "identifierName": "AsyncStorage"
                                  },
                                  "name": "AsyncStorage"
                                },
                                "property": {
                                  "type": "Identifier",
                                  "start": 938,
                                  "end": 948,
                                  "loc": {
                                    "start": {
                                      "line": 34,
                                      "column": 35
                                    },
                                    "end": {
                                      "line": 34,
                                      "column": 45
                                    },
                                    "identifierName": "removeItem"
                                  },
                                  "name": "removeItem"
                                },
                                "computed": false
                              },
                              "arguments": [
                                {
                                  "type": "Identifier",
                                  "start": 949,
                                  "end": 952,
                                  "loc": {
                                    "start": {
                                      "line": 34,
                                      "column": 46
                                    },
                                    "end": {
                                      "line": 34,
                                      "column": 49
                                    },
                                    "identifierName": "key"
                                  },
                                  "name": "key"
                                }
                              ]
                            }
                          }
                        }
                      ],
                      "kind": "const"
                    }
                  ],
                  "directives": []
                }
              },
              "leadingComments": null
            }
          ],
          "kind": "const",
          "leadingComments": [
            {
              "type": "CommentBlock",
              "value": "*\n * This method is used remove data from async storage\n * @param {string} key Unique key for identifying data stored in async storage\n ",
              "start": 721,
              "end": 861,
              "loc": {
                "start": {
                  "line": 29,
                  "column": 0
                },
                "end": {
                  "line": 32,
                  "column": 3
                }
              }
            }
          ],
          "trailingComments": []
        },
        "leadingComments": [
          {
            "type": "CommentBlock",
            "value": "*\n * This method is used remove data from async storage\n * @param {string} key Unique key for identifying data stored in async storage\n ",
            "start": 721,
            "end": 861,
            "loc": {
              "start": {
                "line": 29,
                "column": 0
              },
              "end": {
                "line": 32,
                "column": 3
              }
            }
          }
        ]
      }
    ],
    "directives": []
  },
  "comments": [
    {
      "type": "CommentBlock",
      "value": "*\n * File for handling async storage requests\n ",
      "start": 0,
      "end": 51,
      "loc": {
        "start": {
          "line": 1,
          "column": 0
        },
        "end": {
          "line": 3,
          "column": 3
        }
      }
    },
    {
      "type": "CommentBlock",
      "value": "*\n * Imports\n ",
      "start": 53,
      "end": 71,
      "loc": {
        "start": {
          "line": 5,
          "column": 0
        },
        "end": {
          "line": 7,
          "column": 3
        }
      }
    },
    {
      "type": "CommentBlock",
      "value": "*\n * This method is used to store data in async storage\n * @param {String} key Unique key for identifying data stored in async storage\n * @param {String} data Data to be stored\n ",
      "start": 143,
      "end": 325,
      "loc": {
        "start": {
          "line": 10,
          "column": 0
        },
        "end": {
          "line": 14,
          "column": 3
        }
      }
    },
    {
      "type": "CommentBlock",
      "value": "*\n * This method is used get data from async storage\n * @param {String} key Unique key for identifying data stored in async storage\n * @returns Value obtained from async storage against given key\n ",
      "start": 412,
      "end": 613,
      "loc": {
        "start": {
          "line": 19,
          "column": 0
        },
        "end": {
          "line": 23,
          "column": 3
        }
      }
    },
    {
      "type": "CommentBlock",
      "value": "*\n * This method is used remove data from async storage\n * @param {string} key Unique key for identifying data stored in async storage\n ",
      "start": 721,
      "end": 861,
      "loc": {
        "start": {
          "line": 29,
          "column": 0
        },
        "end": {
          "line": 32,
          "column": 3
        }
      }
    }
  ],
  "tokens": [
    {
      "type": "CommentBlock",
      "value": "*\n * File for handling async storage requests\n ",
      "start": 0,
      "end": 51,
      "loc": {
        "start": {
          "line": 1,
          "column": 0
        },
        "end": {
          "line": 3,
          "column": 3
        }
      }
    },
    {
      "type": "CommentBlock",
      "value": "*\n * Imports\n ",
      "start": 53,
      "end": 71,
      "loc": {
        "start": {
          "line": 5,
          "column": 0
        },
        "end": {
          "line": 7,
          "column": 3
        }
      }
    },
    {
      "type": {
        "label": "import",
        "keyword": "import",
        "beforeExpr": false,
        "startsExpr": true,
        "rightAssociative": false,
        "isLoop": false,
        "isAssign": false,
        "prefix": false,
        "postfix": false,
        "binop": null,
        "updateContext": null
      },
      "value": "import",
      "start": 72,
      "end": 78,
      "loc": {
        "start": {
          "line": 8,
          "column": 0
        },
        "end": {
          "line": 8,
          "column": 6
        }
      }
    },
    {
      "type": {
        "label": "name",
        "beforeExpr": false,
        "startsExpr": true,
        "rightAssociative": false,
        "isLoop": false,
        "isAssign": false,
        "prefix": false,
        "postfix": false,
        "binop": null
      },
      "value": "AsyncStorage",
      "start": 79,
      "end": 91,
      "loc": {
        "start": {
          "line": 8,
          "column": 7
        },
        "end": {
          "line": 8,
          "column": 19
        }
      }
    },
    {
      "type": {
        "label": "name",
        "beforeExpr": false,
        "startsExpr": true,
        "rightAssociative": false,
        "isLoop": false,
        "isAssign": false,
        "prefix": false,
        "postfix": false,
        "binop": null
      },
      "value": "from",
      "start": 92,
      "end": 96,
      "loc": {
        "start": {
          "line": 8,
          "column": 20
        },
        "end": {
          "line": 8,
          "column": 24
        }
      }
    },
    {
      "type": {
        "label": "string",
        "beforeExpr": false,
        "startsExpr": true,
        "rightAssociative": false,
        "isLoop": false,
        "isAssign": false,
        "prefix": false,
        "postfix": false,
        "binop": null,
        "updateContext": null
      },
      "value": "@react-native-async-storage/async-storage",
      "start": 97,
      "end": 140,
      "loc": {
        "start": {
          "line": 8,
          "column": 25
        },
        "end": {
          "line": 8,
          "column": 68
        }
      }
    },
    {
      "type": {
        "label": ";",
        "beforeExpr": true,
        "startsExpr": false,
        "rightAssociative": false,
        "isLoop": false,
        "isAssign": false,
        "prefix": false,
        "postfix": false,
        "binop": null,
        "updateContext": null
      },
      "start": 140,
      "end": 141,
      "loc": {
        "start": {
          "line": 8,
          "column": 68
        },
        "end": {
          "line": 8,
          "column": 69
        }
      }
    },
    {
      "type": "CommentBlock",
      "value": "*\n * This method is used to store data in async storage\n * @param {String} key Unique key for identifying data stored in async storage\n * @param {String} data Data to be stored\n ",
      "start": 143,
      "end": 325,
      "loc": {
        "start": {
          "line": 10,
          "column": 0
        },
        "end": {
          "line": 14,
          "column": 3
        }
      }
    },
    {
      "type": {
        "label": "export",
        "keyword": "export",
        "beforeExpr": false,
        "startsExpr": false,
        "rightAssociative": false,
        "isLoop": false,
        "isAssign": false,
        "prefix": false,
        "postfix": false,
        "binop": null,
        "updateContext": null
      },
      "value": "export",
      "start": 326,
      "end": 332,
      "loc": {
        "start": {
          "line": 15,
          "column": 0
        },
        "end": {
          "line": 15,
          "column": 6
        }
      }
    },
    {
      "type": {
        "label": "const",
        "keyword": "const",
        "beforeExpr": false,
        "startsExpr": false,
        "rightAssociative": false,
        "isLoop": false,
        "isAssign": false,
        "prefix": false,
        "postfix": false,
        "binop": null,
        "updateContext": null
      },
      "value": "const",
      "start": 333,
      "end": 338,
      "loc": {
        "start": {
          "line": 15,
          "column": 7
        },
        "end": {
          "line": 15,
          "column": 12
        }
      }
    },
    {
      "type": {
        "label": "name",
        "beforeExpr": false,
        "startsExpr": true,
        "rightAssociative": false,
        "isLoop": false,
        "isAssign": false,
        "prefix": false,
        "postfix": false,
        "binop": null
      },
      "value": "saveData",
      "start": 339,
      "end": 347,
      "loc": {
        "start": {
          "line": 15,
          "column": 13
        },
        "end": {
          "line": 15,
          "column": 21
        }
      }
    },
    {
      "type": {
        "label": "=",
        "beforeExpr": true,
        "startsExpr": false,
        "rightAssociative": false,
        "isLoop": false,
        "isAssign": true,
        "prefix": false,
        "postfix": false,
        "binop": null,
        "updateContext": null
      },
      "value": "=",
      "start": 348,
      "end": 349,
      "loc": {
        "start": {
          "line": 15,
          "column": 22
        },
        "end": {
          "line": 15,
          "column": 23
        }
      }
    },
    {
      "type": {
        "label": "name",
        "beforeExpr": false,
        "startsExpr": true,
        "rightAssociative": false,
        "isLoop": false,
        "isAssign": false,
        "prefix": false,
        "postfix": false,
        "binop": null
      },
      "value": "async",
      "start": 350,
      "end": 355,
      "loc": {
        "start": {
          "line": 15,
          "column": 24
        },
        "end": {
          "line": 15,
          "column": 29
        }
      }
    },
    {
      "type": {
        "label": "(",
        "beforeExpr": true,
        "startsExpr": true,
        "rightAssociative": false,
        "isLoop": false,
        "isAssign": false,
        "prefix": false,
        "postfix": false,
        "binop": null
      },
      "start": 356,
      "end": 357,
      "loc": {
        "start": {
          "line": 15,
          "column": 30
        },
        "end": {
          "line": 15,
          "column": 31
        }
      }
    },
    {
      "type": {
        "label": "name",
        "beforeExpr": false,
        "startsExpr": true,
        "rightAssociative": false,
        "isLoop": false,
        "isAssign": false,
        "prefix": false,
        "postfix": false,
        "binop": null
      },
      "value": "key",
      "start": 357,
      "end": 360,
      "loc": {
        "start": {
          "line": 15,
          "column": 31
        },
        "end": {
          "line": 15,
          "column": 34
        }
      }
    },
    {
      "type": {
        "label": ",",
        "beforeExpr": true,
        "startsExpr": false,
        "rightAssociative": false,
        "isLoop": false,
        "isAssign": false,
        "prefix": false,
        "postfix": false,
        "binop": null,
        "updateContext": null
      },
      "start": 360,
      "end": 361,
      "loc": {
        "start": {
          "line": 15,
          "column": 34
        },
        "end": {
          "line": 15,
          "column": 35
        }
      }
    },
    {
      "type": {
        "label": "name",
        "beforeExpr": false,
        "startsExpr": true,
        "rightAssociative": false,
        "isLoop": false,
        "isAssign": false,
        "prefix": false,
        "postfix": false,
        "binop": null
      },
      "value": "data",
      "start": 362,
      "end": 366,
      "loc": {
        "start": {
          "line": 15,
          "column": 36
        },
        "end": {
          "line": 15,
          "column": 40
        }
      }
    },
    {
      "type": {
        "label": ")",
        "beforeExpr": false,
        "startsExpr": false,
        "rightAssociative": false,
        "isLoop": false,
        "isAssign": false,
        "prefix": false,
        "postfix": false,
        "binop": null
      },
      "start": 366,
      "end": 367,
      "loc": {
        "start": {
          "line": 15,
          "column": 40
        },
        "end": {
          "line": 15,
          "column": 41
        }
      }
    },
    {
      "type": {
        "label": "=>",
        "beforeExpr": true,
        "startsExpr": false,
        "rightAssociative": false,
        "isLoop": false,
        "isAssign": false,
        "prefix": false,
        "postfix": false,
        "binop": null,
        "updateContext": null
      },
      "start": 368,
      "end": 370,
      "loc": {
        "start": {
          "line": 15,
          "column": 42
        },
        "end": {
          "line": 15,
          "column": 44
        }
      }
    },
    {
      "type": {
        "label": "{",
        "beforeExpr": true,
        "startsExpr": true,
        "rightAssociative": false,
        "isLoop": false,
        "isAssign": false,
        "prefix": false,
        "postfix": false,
        "binop": null
      },
      "start": 371,
      "end": 372,
      "loc": {
        "start": {
          "line": 15,
          "column": 45
        },
        "end": {
          "line": 15,
          "column": 46
        }
      }
    },
    {
      "type": {
        "label": "name",
        "beforeExpr": false,
        "startsExpr": true,
        "rightAssociative": false,
        "isLoop": false,
        "isAssign": false,
        "prefix": false,
        "postfix": false,
        "binop": null
      },
      "value": "AsyncStorage",
      "start": 375,
      "end": 387,
      "loc": {
        "start": {
          "line": 16,
          "column": 2
        },
        "end": {
          "line": 16,
          "column": 14
        }
      }
    },
    {
      "type": {
        "label": ".",
        "beforeExpr": false,
        "startsExpr": false,
        "rightAssociative": false,
        "isLoop": false,
        "isAssign": false,
        "prefix": false,
        "postfix": false,
        "binop": null,
        "updateContext": null
      },
      "start": 387,
      "end": 388,
      "loc": {
        "start": {
          "line": 16,
          "column": 14
        },
        "end": {
          "line": 16,
          "column": 15
        }
      }
    },
    {
      "type": {
        "label": "name",
        "beforeExpr": false,
        "startsExpr": true,
        "rightAssociative": false,
        "isLoop": false,
        "isAssign": false,
        "prefix": false,
        "postfix": false,
        "binop": null
      },
      "value": "setItem",
      "start": 388,
      "end": 395,
      "loc": {
        "start": {
          "line": 16,
          "column": 15
        },
        "end": {
          "line": 16,
          "column": 22
        }
      }
    },
    {
      "type": {
        "label": "(",
        "beforeExpr": true,
        "startsExpr": true,
        "rightAssociative": false,
        "isLoop": false,
        "isAssign": false,
        "prefix": false,
        "postfix": false,
        "binop": null
      },
      "start": 395,
      "end": 396,
      "loc": {
        "start": {
          "line": 16,
          "column": 22
        },
        "end": {
          "line": 16,
          "column": 23
        }
      }
    },
    {
      "type": {
        "label": "name",
        "beforeExpr": false,
        "startsExpr": true,
        "rightAssociative": false,
        "isLoop": false,
        "isAssign": false,
        "prefix": false,
        "postfix": false,
        "binop": null
      },
      "value": "key",
      "start": 396,
      "end": 399,
      "loc": {
        "start": {
          "line": 16,
          "column": 23
        },
        "end": {
          "line": 16,
          "column": 26
        }
      }
    },
    {
      "type": {
        "label": ",",
        "beforeExpr": true,
        "startsExpr": false,
        "rightAssociative": false,
        "isLoop": false,
        "isAssign": false,
        "prefix": false,
        "postfix": false,
        "binop": null,
        "updateContext": null
      },
      "start": 399,
      "end": 400,
      "loc": {
        "start": {
          "line": 16,
          "column": 26
        },
        "end": {
          "line": 16,
          "column": 27
        }
      }
    },
    {
      "type": {
        "label": "name",
        "beforeExpr": false,
        "startsExpr": true,
        "rightAssociative": false,
        "isLoop": false,
        "isAssign": false,
        "prefix": false,
        "postfix": false,
        "binop": null
      },
      "value": "data",
      "start": 401,
      "end": 405,
      "loc": {
        "start": {
          "line": 16,
          "column": 28
        },
        "end": {
          "line": 16,
          "column": 32
        }
      }
    },
    {
      "type": {
        "label": ")",
        "beforeExpr": false,
        "startsExpr": false,
        "rightAssociative": false,
        "isLoop": false,
        "isAssign": false,
        "prefix": false,
        "postfix": false,
        "binop": null
      },
      "start": 405,
      "end": 406,
      "loc": {
        "start": {
          "line": 16,
          "column": 32
        },
        "end": {
          "line": 16,
          "column": 33
        }
      }
    },
    {
      "type": {
        "label": ";",
        "beforeExpr": true,
        "startsExpr": false,
        "rightAssociative": false,
        "isLoop": false,
        "isAssign": false,
        "prefix": false,
        "postfix": false,
        "binop": null,
        "updateContext": null
      },
      "start": 406,
      "end": 407,
      "loc": {
        "start": {
          "line": 16,
          "column": 33
        },
        "end": {
          "line": 16,
          "column": 34
        }
      }
    },
    {
      "type": {
        "label": "}",
        "beforeExpr": false,
        "startsExpr": false,
        "rightAssociative": false,
        "isLoop": false,
        "isAssign": false,
        "prefix": false,
        "postfix": false,
        "binop": null
      },
      "start": 408,
      "end": 409,
      "loc": {
        "start": {
          "line": 17,
          "column": 0
        },
        "end": {
          "line": 17,
          "column": 1
        }
      }
    },
    {
      "type": {
        "label": ";",
        "beforeExpr": true,
        "startsExpr": false,
        "rightAssociative": false,
        "isLoop": false,
        "isAssign": false,
        "prefix": false,
        "postfix": false,
        "binop": null,
        "updateContext": null
      },
      "start": 409,
      "end": 410,
      "loc": {
        "start": {
          "line": 17,
          "column": 1
        },
        "end": {
          "line": 17,
          "column": 2
        }
      }
    },
    {
      "type": "CommentBlock",
      "value": "*\n * This method is used get data from async storage\n * @param {String} key Unique key for identifying data stored in async storage\n * @returns Value obtained from async storage against given key\n ",
      "start": 412,
      "end": 613,
      "loc": {
        "start": {
          "line": 19,
          "column": 0
        },
        "end": {
          "line": 23,
          "column": 3
        }
      }
    },
    {
      "type": {
        "label": "export",
        "keyword": "export",
        "beforeExpr": false,
        "startsExpr": false,
        "rightAssociative": false,
        "isLoop": false,
        "isAssign": false,
        "prefix": false,
        "postfix": false,
        "binop": null,
        "updateContext": null
      },
      "value": "export",
      "start": 614,
      "end": 620,
      "loc": {
        "start": {
          "line": 24,
          "column": 0
        },
        "end": {
          "line": 24,
          "column": 6
        }
      }
    },
    {
      "type": {
        "label": "const",
        "keyword": "const",
        "beforeExpr": false,
        "startsExpr": false,
        "rightAssociative": false,
        "isLoop": false,
        "isAssign": false,
        "prefix": false,
        "postfix": false,
        "binop": null,
        "updateContext": null
      },
      "value": "const",
      "start": 621,
      "end": 626,
      "loc": {
        "start": {
          "line": 24,
          "column": 7
        },
        "end": {
          "line": 24,
          "column": 12
        }
      }
    },
    {
      "type": {
        "label": "name",
        "beforeExpr": false,
        "startsExpr": true,
        "rightAssociative": false,
        "isLoop": false,
        "isAssign": false,
        "prefix": false,
        "postfix": false,
        "binop": null
      },
      "value": "getData",
      "start": 627,
      "end": 634,
      "loc": {
        "start": {
          "line": 24,
          "column": 13
        },
        "end": {
          "line": 24,
          "column": 20
        }
      }
    },
    {
      "type": {
        "label": "=",
        "beforeExpr": true,
        "startsExpr": false,
        "rightAssociative": false,
        "isLoop": false,
        "isAssign": true,
        "prefix": false,
        "postfix": false,
        "binop": null,
        "updateContext": null
      },
      "value": "=",
      "start": 635,
      "end": 636,
      "loc": {
        "start": {
          "line": 24,
          "column": 21
        },
        "end": {
          "line": 24,
          "column": 22
        }
      }
    },
    {
      "type": {
        "label": "name",
        "beforeExpr": false,
        "startsExpr": true,
        "rightAssociative": false,
        "isLoop": false,
        "isAssign": false,
        "prefix": false,
        "postfix": false,
        "binop": null
      },
      "value": "async",
      "start": 637,
      "end": 642,
      "loc": {
        "start": {
          "line": 24,
          "column": 23
        },
        "end": {
          "line": 24,
          "column": 28
        }
      }
    },
    {
      "type": {
        "label": "name",
        "beforeExpr": false,
        "startsExpr": true,
        "rightAssociative": false,
        "isLoop": false,
        "isAssign": false,
        "prefix": false,
        "postfix": false,
        "binop": null
      },
      "value": "key",
      "start": 643,
      "end": 646,
      "loc": {
        "start": {
          "line": 24,
          "column": 29
        },
        "end": {
          "line": 24,
          "column": 32
        }
      }
    },
    {
      "type": {
        "label": "=>",
        "beforeExpr": true,
        "startsExpr": false,
        "rightAssociative": false,
        "isLoop": false,
        "isAssign": false,
        "prefix": false,
        "postfix": false,
        "binop": null,
        "updateContext": null
      },
      "start": 647,
      "end": 649,
      "loc": {
        "start": {
          "line": 24,
          "column": 33
        },
        "end": {
          "line": 24,
          "column": 35
        }
      }
    },
    {
      "type": {
        "label": "{",
        "beforeExpr": true,
        "startsExpr": true,
        "rightAssociative": false,
        "isLoop": false,
        "isAssign": false,
        "prefix": false,
        "postfix": false,
        "binop": null
      },
      "start": 650,
      "end": 651,
      "loc": {
        "start": {
          "line": 24,
          "column": 36
        },
        "end": {
          "line": 24,
          "column": 37
        }
      }
    },
    {
      "type": {
        "label": "const",
        "keyword": "const",
        "beforeExpr": false,
        "startsExpr": false,
        "rightAssociative": false,
        "isLoop": false,
        "isAssign": false,
        "prefix": false,
        "postfix": false,
        "binop": null,
        "updateContext": null
      },
      "value": "const",
      "start": 654,
      "end": 659,
      "loc": {
        "start": {
          "line": 25,
          "column": 2
        },
        "end": {
          "line": 25,
          "column": 7
        }
      }
    },
    {
      "type": {
        "label": "name",
        "beforeExpr": false,
        "startsExpr": true,
        "rightAssociative": false,
        "isLoop": false,
        "isAssign": false,
        "prefix": false,
        "postfix": false,
        "binop": null
      },
      "value": "value",
      "start": 660,
      "end": 665,
      "loc": {
        "start": {
          "line": 25,
          "column": 8
        },
        "end": {
          "line": 25,
          "column": 13
        }
      }
    },
    {
      "type": {
        "label": "=",
        "beforeExpr": true,
        "startsExpr": false,
        "rightAssociative": false,
        "isLoop": false,
        "isAssign": true,
        "prefix": false,
        "postfix": false,
        "binop": null,
        "updateContext": null
      },
      "value": "=",
      "start": 666,
      "end": 667,
      "loc": {
        "start": {
          "line": 25,
          "column": 14
        },
        "end": {
          "line": 25,
          "column": 15
        }
      }
    },
    {
      "type": {
        "label": "name",
        "beforeExpr": false,
        "startsExpr": true,
        "rightAssociative": false,
        "isLoop": false,
        "isAssign": false,
        "prefix": false,
        "postfix": false,
        "binop": null
      },
      "value": "await",
      "start": 668,
      "end": 673,
      "loc": {
        "start": {
          "line": 25,
          "column": 16
        },
        "end": {
          "line": 25,
          "column": 21
        }
      }
    },
    {
      "type": {
        "label": "name",
        "beforeExpr": false,
        "startsExpr": true,
        "rightAssociative": false,
        "isLoop": false,
        "isAssign": false,
        "prefix": false,
        "postfix": false,
        "binop": null
      },
      "value": "AsyncStorage",
      "start": 674,
      "end": 686,
      "loc": {
        "start": {
          "line": 25,
          "column": 22
        },
        "end": {
          "line": 25,
          "column": 34
        }
      }
    },
    {
      "type": {
        "label": ".",
        "beforeExpr": false,
        "startsExpr": false,
        "rightAssociative": false,
        "isLoop": false,
        "isAssign": false,
        "prefix": false,
        "postfix": false,
        "binop": null,
        "updateContext": null
      },
      "start": 686,
      "end": 687,
      "loc": {
        "start": {
          "line": 25,
          "column": 34
        },
        "end": {
          "line": 25,
          "column": 35
        }
      }
    },
    {
      "type": {
        "label": "name",
        "beforeExpr": false,
        "startsExpr": true,
        "rightAssociative": false,
        "isLoop": false,
        "isAssign": false,
        "prefix": false,
        "postfix": false,
        "binop": null
      },
      "value": "getItem",
      "start": 687,
      "end": 694,
      "loc": {
        "start": {
          "line": 25,
          "column": 35
        },
        "end": {
          "line": 25,
          "column": 42
        }
      }
    },
    {
      "type": {
        "label": "(",
        "beforeExpr": true,
        "startsExpr": true,
        "rightAssociative": false,
        "isLoop": false,
        "isAssign": false,
        "prefix": false,
        "postfix": false,
        "binop": null
      },
      "start": 694,
      "end": 695,
      "loc": {
        "start": {
          "line": 25,
          "column": 42
        },
        "end": {
          "line": 25,
          "column": 43
        }
      }
    },
    {
      "type": {
        "label": "name",
        "beforeExpr": false,
        "startsExpr": true,
        "rightAssociative": false,
        "isLoop": false,
        "isAssign": false,
        "prefix": false,
        "postfix": false,
        "binop": null
      },
      "value": "key",
      "start": 695,
      "end": 698,
      "loc": {
        "start": {
          "line": 25,
          "column": 43
        },
        "end": {
          "line": 25,
          "column": 46
        }
      }
    },
    {
      "type": {
        "label": ")",
        "beforeExpr": false,
        "startsExpr": false,
        "rightAssociative": false,
        "isLoop": false,
        "isAssign": false,
        "prefix": false,
        "postfix": false,
        "binop": null
      },
      "start": 698,
      "end": 699,
      "loc": {
        "start": {
          "line": 25,
          "column": 46
        },
        "end": {
          "line": 25,
          "column": 47
        }
      }
    },
    {
      "type": {
        "label": ";",
        "beforeExpr": true,
        "startsExpr": false,
        "rightAssociative": false,
        "isLoop": false,
        "isAssign": false,
        "prefix": false,
        "postfix": false,
        "binop": null,
        "updateContext": null
      },
      "start": 699,
      "end": 700,
      "loc": {
        "start": {
          "line": 25,
          "column": 47
        },
        "end": {
          "line": 25,
          "column": 48
        }
      }
    },
    {
      "type": {
        "label": "return",
        "keyword": "return",
        "beforeExpr": true,
        "startsExpr": false,
        "rightAssociative": false,
        "isLoop": false,
        "isAssign": false,
        "prefix": false,
        "postfix": false,
        "binop": null,
        "updateContext": null
      },
      "value": "return",
      "start": 703,
      "end": 709,
      "loc": {
        "start": {
          "line": 26,
          "column": 2
        },
        "end": {
          "line": 26,
          "column": 8
        }
      }
    },
    {
      "type": {
        "label": "name",
        "beforeExpr": false,
        "startsExpr": true,
        "rightAssociative": false,
        "isLoop": false,
        "isAssign": false,
        "prefix": false,
        "postfix": false,
        "binop": null
      },
      "value": "value",
      "start": 710,
      "end": 715,
      "loc": {
        "start": {
          "line": 26,
          "column": 9
        },
        "end": {
          "line": 26,
          "column": 14
        }
      }
    },
    {
      "type": {
        "label": ";",
        "beforeExpr": true,
        "startsExpr": false,
        "rightAssociative": false,
        "isLoop": false,
        "isAssign": false,
        "prefix": false,
        "postfix": false,
        "binop": null,
        "updateContext": null
      },
      "start": 715,
      "end": 716,
      "loc": {
        "start": {
          "line": 26,
          "column": 14
        },
        "end": {
          "line": 26,
          "column": 15
        }
      }
    },
    {
      "type": {
        "label": "}",
        "beforeExpr": false,
        "startsExpr": false,
        "rightAssociative": false,
        "isLoop": false,
        "isAssign": false,
        "prefix": false,
        "postfix": false,
        "binop": null
      },
      "start": 717,
      "end": 718,
      "loc": {
        "start": {
          "line": 27,
          "column": 0
        },
        "end": {
          "line": 27,
          "column": 1
        }
      }
    },
    {
      "type": {
        "label": ";",
        "beforeExpr": true,
        "startsExpr": false,
        "rightAssociative": false,
        "isLoop": false,
        "isAssign": false,
        "prefix": false,
        "postfix": false,
        "binop": null,
        "updateContext": null
      },
      "start": 718,
      "end": 719,
      "loc": {
        "start": {
          "line": 27,
          "column": 1
        },
        "end": {
          "line": 27,
          "column": 2
        }
      }
    },
    {
      "type": "CommentBlock",
      "value": "*\n * This method is used remove data from async storage\n * @param {string} key Unique key for identifying data stored in async storage\n ",
      "start": 721,
      "end": 861,
      "loc": {
        "start": {
          "line": 29,
          "column": 0
        },
        "end": {
          "line": 32,
          "column": 3
        }
      }
    },
    {
      "type": {
        "label": "export",
        "keyword": "export",
        "beforeExpr": false,
        "startsExpr": false,
        "rightAssociative": false,
        "isLoop": false,
        "isAssign": false,
        "prefix": false,
        "postfix": false,
        "binop": null,
        "updateContext": null
      },
      "value": "export",
      "start": 862,
      "end": 868,
      "loc": {
        "start": {
          "line": 33,
          "column": 0
        },
        "end": {
          "line": 33,
          "column": 6
        }
      }
    },
    {
      "type": {
        "label": "const",
        "keyword": "const",
        "beforeExpr": false,
        "startsExpr": false,
        "rightAssociative": false,
        "isLoop": false,
        "isAssign": false,
        "prefix": false,
        "postfix": false,
        "binop": null,
        "updateContext": null
      },
      "value": "const",
      "start": 869,
      "end": 874,
      "loc": {
        "start": {
          "line": 33,
          "column": 7
        },
        "end": {
          "line": 33,
          "column": 12
        }
      }
    },
    {
      "type": {
        "label": "name",
        "beforeExpr": false,
        "startsExpr": true,
        "rightAssociative": false,
        "isLoop": false,
        "isAssign": false,
        "prefix": false,
        "postfix": false,
        "binop": null
      },
      "value": "removeData",
      "start": 875,
      "end": 885,
      "loc": {
        "start": {
          "line": 33,
          "column": 13
        },
        "end": {
          "line": 33,
          "column": 23
        }
      }
    },
    {
      "type": {
        "label": "=",
        "beforeExpr": true,
        "startsExpr": false,
        "rightAssociative": false,
        "isLoop": false,
        "isAssign": true,
        "prefix": false,
        "postfix": false,
        "binop": null,
        "updateContext": null
      },
      "value": "=",
      "start": 886,
      "end": 887,
      "loc": {
        "start": {
          "line": 33,
          "column": 24
        },
        "end": {
          "line": 33,
          "column": 25
        }
      }
    },
    {
      "type": {
        "label": "name",
        "beforeExpr": false,
        "startsExpr": true,
        "rightAssociative": false,
        "isLoop": false,
        "isAssign": false,
        "prefix": false,
        "postfix": false,
        "binop": null
      },
      "value": "async",
      "start": 888,
      "end": 893,
      "loc": {
        "start": {
          "line": 33,
          "column": 26
        },
        "end": {
          "line": 33,
          "column": 31
        }
      }
    },
    {
      "type": {
        "label": "name",
        "beforeExpr": false,
        "startsExpr": true,
        "rightAssociative": false,
        "isLoop": false,
        "isAssign": false,
        "prefix": false,
        "postfix": false,
        "binop": null
      },
      "value": "key",
      "start": 894,
      "end": 897,
      "loc": {
        "start": {
          "line": 33,
          "column": 32
        },
        "end": {
          "line": 33,
          "column": 35
        }
      }
    },
    {
      "type": {
        "label": "=>",
        "beforeExpr": true,
        "startsExpr": false,
        "rightAssociative": false,
        "isLoop": false,
        "isAssign": false,
        "prefix": false,
        "postfix": false,
        "binop": null,
        "updateContext": null
      },
      "start": 898,
      "end": 900,
      "loc": {
        "start": {
          "line": 33,
          "column": 36
        },
        "end": {
          "line": 33,
          "column": 38
        }
      }
    },
    {
      "type": {
        "label": "{",
        "beforeExpr": true,
        "startsExpr": true,
        "rightAssociative": false,
        "isLoop": false,
        "isAssign": false,
        "prefix": false,
        "postfix": false,
        "binop": null
      },
      "start": 901,
      "end": 902,
      "loc": {
        "start": {
          "line": 33,
          "column": 39
        },
        "end": {
          "line": 33,
          "column": 40
        }
      }
    },
    {
      "type": {
        "label": "const",
        "keyword": "const",
        "beforeExpr": false,
        "startsExpr": false,
        "rightAssociative": false,
        "isLoop": false,
        "isAssign": false,
        "prefix": false,
        "postfix": false,
        "binop": null,
        "updateContext": null
      },
      "value": "const",
      "start": 905,
      "end": 910,
      "loc": {
        "start": {
          "line": 34,
          "column": 2
        },
        "end": {
          "line": 34,
          "column": 7
        }
      }
    },
    {
      "type": {
        "label": "name",
        "beforeExpr": false,
        "startsExpr": true,
        "rightAssociative": false,
        "isLoop": false,
        "isAssign": false,
        "prefix": false,
        "postfix": false,
        "binop": null
      },
      "value": "value",
      "start": 911,
      "end": 916,
      "loc": {
        "start": {
          "line": 34,
          "column": 8
        },
        "end": {
          "line": 34,
          "column": 13
        }
      }
    },
    {
      "type": {
        "label": "=",
        "beforeExpr": true,
        "startsExpr": false,
        "rightAssociative": false,
        "isLoop": false,
        "isAssign": true,
        "prefix": false,
        "postfix": false,
        "binop": null,
        "updateContext": null
      },
      "value": "=",
      "start": 917,
      "end": 918,
      "loc": {
        "start": {
          "line": 34,
          "column": 14
        },
        "end": {
          "line": 34,
          "column": 15
        }
      }
    },
    {
      "type": {
        "label": "name",
        "beforeExpr": false,
        "startsExpr": true,
        "rightAssociative": false,
        "isLoop": false,
        "isAssign": false,
        "prefix": false,
        "postfix": false,
        "binop": null
      },
      "value": "await",
      "start": 919,
      "end": 924,
      "loc": {
        "start": {
          "line": 34,
          "column": 16
        },
        "end": {
          "line": 34,
          "column": 21
        }
      }
    },
    {
      "type": {
        "label": "name",
        "beforeExpr": false,
        "startsExpr": true,
        "rightAssociative": false,
        "isLoop": false,
        "isAssign": false,
        "prefix": false,
        "postfix": false,
        "binop": null
      },
      "value": "AsyncStorage",
      "start": 925,
      "end": 937,
      "loc": {
        "start": {
          "line": 34,
          "column": 22
        },
        "end": {
          "line": 34,
          "column": 34
        }
      }
    },
    {
      "type": {
        "label": ".",
        "beforeExpr": false,
        "startsExpr": false,
        "rightAssociative": false,
        "isLoop": false,
        "isAssign": false,
        "prefix": false,
        "postfix": false,
        "binop": null,
        "updateContext": null
      },
      "start": 937,
      "end": 938,
      "loc": {
        "start": {
          "line": 34,
          "column": 34
        },
        "end": {
          "line": 34,
          "column": 35
        }
      }
    },
    {
      "type": {
        "label": "name",
        "beforeExpr": false,
        "startsExpr": true,
        "rightAssociative": false,
        "isLoop": false,
        "isAssign": false,
        "prefix": false,
        "postfix": false,
        "binop": null
      },
      "value": "removeItem",
      "start": 938,
      "end": 948,
      "loc": {
        "start": {
          "line": 34,
          "column": 35
        },
        "end": {
          "line": 34,
          "column": 45
        }
      }
    },
    {
      "type": {
        "label": "(",
        "beforeExpr": true,
        "startsExpr": true,
        "rightAssociative": false,
        "isLoop": false,
        "isAssign": false,
        "prefix": false,
        "postfix": false,
        "binop": null
      },
      "start": 948,
      "end": 949,
      "loc": {
        "start": {
          "line": 34,
          "column": 45
        },
        "end": {
          "line": 34,
          "column": 46
        }
      }
    },
    {
      "type": {
        "label": "name",
        "beforeExpr": false,
        "startsExpr": true,
        "rightAssociative": false,
        "isLoop": false,
        "isAssign": false,
        "prefix": false,
        "postfix": false,
        "binop": null
      },
      "value": "key",
      "start": 949,
      "end": 952,
      "loc": {
        "start": {
          "line": 34,
          "column": 46
        },
        "end": {
          "line": 34,
          "column": 49
        }
      }
    },
    {
      "type": {
        "label": ")",
        "beforeExpr": false,
        "startsExpr": false,
        "rightAssociative": false,
        "isLoop": false,
        "isAssign": false,
        "prefix": false,
        "postfix": false,
        "binop": null
      },
      "start": 952,
      "end": 953,
      "loc": {
        "start": {
          "line": 34,
          "column": 49
        },
        "end": {
          "line": 34,
          "column": 50
        }
      }
    },
    {
      "type": {
        "label": ";",
        "beforeExpr": true,
        "startsExpr": false,
        "rightAssociative": false,
        "isLoop": false,
        "isAssign": false,
        "prefix": false,
        "postfix": false,
        "binop": null,
        "updateContext": null
      },
      "start": 953,
      "end": 954,
      "loc": {
        "start": {
          "line": 34,
          "column": 50
        },
        "end": {
          "line": 34,
          "column": 51
        }
      }
    },
    {
      "type": {
        "label": "}",
        "beforeExpr": false,
        "startsExpr": false,
        "rightAssociative": false,
        "isLoop": false,
        "isAssign": false,
        "prefix": false,
        "postfix": false,
        "binop": null
      },
      "start": 955,
      "end": 956,
      "loc": {
        "start": {
          "line": 35,
          "column": 0
        },
        "end": {
          "line": 35,
          "column": 1
        }
      }
    },
    {
      "type": {
        "label": ";",
        "beforeExpr": true,
        "startsExpr": false,
        "rightAssociative": false,
        "isLoop": false,
        "isAssign": false,
        "prefix": false,
        "postfix": false,
        "binop": null,
        "updateContext": null
      },
      "start": 956,
      "end": 957,
      "loc": {
        "start": {
          "line": 35,
          "column": 1
        },
        "end": {
          "line": 35,
          "column": 2
        }
      }
    },
    {
      "type": {
        "label": "eof",
        "beforeExpr": false,
        "startsExpr": false,
        "rightAssociative": false,
        "isLoop": false,
        "isAssign": false,
        "prefix": false,
        "postfix": false,
        "binop": null,
        "updateContext": null
      },
      "start": 958,
      "end": 958,
      "loc": {
        "start": {
          "line": 36,
          "column": 0
        },
        "end": {
          "line": 36,
          "column": 0
        }
      }
    }
  ]
}